xww/__init__.py
xww/demo1.py
xww/demo2.py
xww-1.0.dist-info/METADATA
xww-1.0.dist-info/WHEEL
xww-1.0.dist-info/top_level.txt
xww-1.0.dist-info/RECORD
