Metadata-Version: 2.1
Name: xww
Version: 1.0
Summary: 这是第一个对外发布的模板，测试
Author: xww
Author-email: 2541228551@qq.com
